gtdbtk_db_download
